census_data_aggregator/__init__.py
census_data_aggregator/exceptions.py
census_data_aggregator-0.0.8.dist-info/LICENSE
census_data_aggregator-0.0.8.dist-info/METADATA
census_data_aggregator-0.0.8.dist-info/WHEEL
census_data_aggregator-0.0.8.dist-info/top_level.txt
census_data_aggregator-0.0.8.dist-info/RECORD
